ghq/__init__.py
ghq/multivariate.py
ghq/univariate.py
ghq-0.0.5.dist-info/LICENSE
ghq-0.0.5.dist-info/METADATA
ghq-0.0.5.dist-info/WHEEL
ghq-0.0.5.dist-info/top_level.txt
ghq-0.0.5.dist-info/RECORD
