Metadata-Version: 2.1
Name: ghq
Version: 0.0.5
Summary: Gauss-Hermite quadrature in JAX
Author-email: Sam Duffield <s@mduffield.com>
License: Apache-2.0
Project-URL: Homepage, https://github.com/SamDuffield/ghq
Project-URL: Repository, https://github.com/SamDuffield/ghq
Keywords: jax,integration,quadrature
Classifier: Programming Language :: Python :: 3
Classifier: Topic :: Scientific/Engineering :: Mathematics
Classifier: License :: OSI Approved :: Apache Software License
Requires-Python: ~=3.9
License-File: LICENSE
Requires-Dist: jax>=0.4.13
